dinosaur_pygame/__init__.py
dinosaur_pygame/main.py
dinosaur_pygame/requirements.txt
dinosaur_pygame/first_version/.DS_Store
dinosaur_pygame/first_version/dinosaurio.py
dinosaur_pygame/first_version/images/.DS_Store
dinosaur_pygame/first_version/images/dinosaurio.png
dinosaur_pygame/first_version/images/fondo.jpg
dinosaur_pygame/first_version/images/jamon.png
dinosaur_pygame/first_version/images/meteorito.png
dinosaur_pygame/first_version/images/meteoritoGordo.png
dinosaur_pygame/images/.DS_Store
dinosaur_pygame/images/background.png
dinosaur_pygame/images/dinosaur.png
dinosaur_pygame/images/ham.png
dinosaur_pygame/images/meteor-big.png
dinosaur_pygame/images/meteor.png
dinosaur_pygame-0.0.9.dist-info/LICENSE
dinosaur_pygame-0.0.9.dist-info/METADATA
dinosaur_pygame-0.0.9.dist-info/WHEEL
dinosaur_pygame-0.0.9.dist-info/entry_points.txt
dinosaur_pygame-0.0.9.dist-info/top_level.txt
dinosaur_pygame-0.0.9.dist-info/RECORD
