Metadata-Version: 2.1
Name: dinosaur-pygame
Version: 0.0.9
Summary: A dinosaur game made with pygame
Home-page: https://github.com/albertomsp/dinosaur-pygame
Author: Alberto Morales
Author-email: albertomoralessp@gmail.com
License: UNKNOWN
Platform: UNKNOWN
Classifier: Programming Language :: Python :: 3
Classifier: License :: OSI Approved :: MIT License
Classifier: Operating System :: OS Independent
Requires-Python: >=3.5
Requires-Dist: pygame (>=2.0.0.dev4)
